LICENSE.txt
MANIFEST.in
README.rst
setup.py
django_simple_friends.egg-info/PKG-INFO
django_simple_friends.egg-info/SOURCES.txt
django_simple_friends.egg-info/dependency_links.txt
django_simple_friends.egg-info/requires.txt
django_simple_friends.egg-info/top_level.txt
friends/__init__.py
friends/admin.py
friends/app_settings.py
friends/management.py
friends/models.py
friends/signals.py
friends/tests.py
friends/urls.py
friends/views.py
friends/fixtures/test_data.json
friends/locale/de/LC_MESSAGES/django.mo
friends/locale/de/LC_MESSAGES/django.po
friends/locale/es/LC_MESSAGES/django.mo
friends/locale/es/LC_MESSAGES/django.po
friends/locale/tr/LC_MESSAGES/django.mo
friends/locale/tr/LC_MESSAGES/django.po
friends/templatetags/__init__.py
friends/templatetags/friends_tags.py