Metadata-Version: 1.1
Name: django-simple-friends
Version: 1.1.1
Summary: Like django-friends, but simpler
Home-page: http://github.com/muhuk/django-simple-friends
Author: Atamert Ölçgen
Author-email: muhuk@muhuk.com
License: Copyright (c) 2006, Atamert Ölçgen (http://www.muhuk.com)
